quick_colorpicker/__init__.py
quick_colorpicker/main.py
quick_colorpicker-1.0.3.dist-info/METADATA
quick_colorpicker-1.0.3.dist-info/WHEEL
quick_colorpicker-1.0.3.dist-info/entry_points.txt
quick_colorpicker-1.0.3.dist-info/top_level.txt
quick_colorpicker-1.0.3.dist-info/RECORD
