Metadata-Version: 2.4
Name: quick-colorpicker
Version: 1.0.3
Summary: A professional cross-platform color picking utility
Home-page: https://github.com/Monstertov/quick-colorpicker
Author: Monstertov
Author-email: rob@monstertov.nl
Classifier: Development Status :: 5 - Production/Stable
Classifier: Intended Audience :: Developers
Classifier: Intended Audience :: End Users/Desktop
Classifier: Topic :: Multimedia :: Graphics
Classifier: Topic :: Utilities
Classifier: Programming Language :: Python :: 3
Classifier: Programming Language :: Python :: 3.6
Classifier: Programming Language :: Python :: 3.7
Classifier: Programming Language :: Python :: 3.8
Classifier: Programming Language :: Python :: 3.9
Classifier: Programming Language :: Python :: 3.10
Classifier: Programming Language :: Python :: 3.11
Classifier: Programming Language :: Python :: 3.12
Classifier: Programming Language :: Python :: 3.13
Classifier: License :: OSI Approved :: MIT License
Classifier: Operating System :: OS Independent
Classifier: Environment :: Console
Requires-Python: >=3.6
Requires-Dist: pynput==1.7.6
Requires-Dist: pyautogui==0.9.54
Requires-Dist: Pillow==10.2.0
Requires-Dist: pyperclip>=1.8.2
Requires-Dist: rich>=12.0.0
Dynamic: author
Dynamic: author-email
Dynamic: classifier
Dynamic: description
Dynamic: description-content-type
Dynamic: home-page
Dynamic: requires-dist
Dynamic: requires-python
Dynamic: summary
